clana/__init__.py
clana/__main__.py
clana/cli.py
clana/clustering.py
clana/cm_metrics.py
clana/config.yaml
clana/distribution.py
clana/get_cm.py
clana/get_cm_simple.py
clana/io.py
clana/optimize.py
clana/utils.py
clana/visualize_cm.py
clana-0.4.1.dist-info/LICENSE
clana-0.4.1.dist-info/METADATA
clana-0.4.1.dist-info/WHEEL
clana-0.4.1.dist-info/entry_points.txt
clana-0.4.1.dist-info/top_level.txt
clana-0.4.1.dist-info/RECORD
