Metadata-Version: 2.1
Name: clana
Version: 0.4.1
Summary: CLANA is a toolkit for classifier analysis.
Home-page: https://github.com/MartinThoma/clana
Author: Martin Thoma
Author-email: info@martin-thoma.de
Maintainer: Martin Thoma
Maintainer-email: info@martin-thoma.de
License: MIT
Download-URL: https://github.com/MartinThoma/clana
Keywords: Machine Learning,Data Science,classifiers,Classification,Classifier Analysis
Platform: Linux
Classifier: Development Status :: 4 - Beta
Classifier: Environment :: Console
Classifier: Intended Audience :: Developers
Classifier: Intended Audience :: Information Technology
Classifier: Intended Audience :: Science/Research
Classifier: License :: OSI Approved :: MIT License
Classifier: Natural Language :: English
Classifier: Operating System :: OS Independent
Classifier: Programming Language :: Python :: 3
Classifier: Programming Language :: Python :: 3 :: Only
Classifier: Programming Language :: Python :: 3.7
Classifier: Programming Language :: Python :: 3.8
Classifier: Programming Language :: Python :: 3.9
Classifier: Topic :: Software Development :: Libraries :: Python Modules
Classifier: Topic :: Scientific/Engineering :: Information Analysis
Classifier: Topic :: Scientific/Engineering :: Visualization
Classifier: Topic :: Software Development
Classifier: Topic :: Utilities
Requires-Python: >=3.6
Requires-Dist: click (>=6.7)
Requires-Dist: jinja2
Requires-Dist: matplotlib (>=2.1.1)
Requires-Dist: numpy (>=1.20.0)
Requires-Dist: PyYAML (>=5.1.1)
Requires-Dist: scikit-learn (>=0.19.1)
Requires-Dist: scipy (>=1.0.0)
